cs_ob_mini_scikit_learn/__init__.py
cs_ob_mini_scikit_learn/cctest.py
cs_ob_mini_scikit_learn/clone.py
cs_ob_mini_scikit_learn/ensemble/AdaBoost.py
cs_ob_mini_scikit_learn/ensemble/GradientBoostingClassifier.py
cs_ob_mini_scikit_learn/ensemble/GradientBoostingRegressor.py
cs_ob_mini_scikit_learn/ensemble/RandomForestClassifier.py
cs_ob_mini_scikit_learn/ensemble/RandomForestRegressor.py
cs_ob_mini_scikit_learn/ensemble/StackingClassifier.py
cs_ob_mini_scikit_learn/ensemble/VotingClassifier.py
cs_ob_mini_scikit_learn/ensemble/__init__.py
cs_ob_mini_scikit_learn/metrics/Accuracy.py
cs_ob_mini_scikit_learn/metrics/BaseMetric.py
cs_ob_mini_scikit_learn/metrics/ConfusionMatrix.py
cs_ob_mini_scikit_learn/metrics/F1Score.py
cs_ob_mini_scikit_learn/metrics/MeanAbsoluteError.py
cs_ob_mini_scikit_learn/metrics/MeanSquaredError.py
cs_ob_mini_scikit_learn/metrics/Precision.py
cs_ob_mini_scikit_learn/metrics/RSquared.py
cs_ob_mini_scikit_learn/metrics/Recall.py
cs_ob_mini_scikit_learn/metrics/RootMeanSquaredError.py
cs_ob_mini_scikit_learn/metrics/__init__.py
cs_ob_mini_scikit_learn/model_selection/GridSearchCV.py
cs_ob_mini_scikit_learn/model_selection/KFold.py
cs_ob_mini_scikit_learn/model_selection/ParameterGrid.py
cs_ob_mini_scikit_learn/model_selection/__init__.py
cs_ob_mini_scikit_learn/model_selection/train_test_split.py
cs_ob_mini_scikit_learn/neural_networks/MLP.py
cs_ob_mini_scikit_learn/neural_networks/MLPRegressor.py
cs_ob_mini_scikit_learn/neural_networks/Perceptron.py
cs_ob_mini_scikit_learn/neural_networks/__init__.py
cs_ob_mini_scikit_learn/preprocessing/LabelEncoder.py
cs_ob_mini_scikit_learn/preprocessing/MinMaxScaler.py
cs_ob_mini_scikit_learn/preprocessing/OneHotEncoder.py
cs_ob_mini_scikit_learn/preprocessing/SimpleImputer.py
cs_ob_mini_scikit_learn/preprocessing/StandardScaler.py
cs_ob_mini_scikit_learn/preprocessing/__init__.py
cs_ob_mini_scikit_learn/supervised_learning/BaseEstimator.py
cs_ob_mini_scikit_learn/supervised_learning/__init__.py
cs_ob_mini_scikit_learn-0.1.11.dist-info/METADATA
cs_ob_mini_scikit_learn-0.1.11.dist-info/WHEEL
cs_ob_mini_scikit_learn-0.1.11.dist-info/top_level.txt
cs_ob_mini_scikit_learn-0.1.11.dist-info/RECORD
