Metadata-Version: 2.1
Name: cs-ob-mini-scikit-learn
Version: 0.1.11
Summary: A minimal implementation of scikit-learn like functionalities
Home-page: https://github.com/Basma-Arnaoui/Mini-Scikit-Learn/tree/main
Author: basma-arnaoui
Author-email: basma.arnaoui@um6p.ma
License: UNKNOWN
Platform: UNKNOWN
Requires-Python: >=3.6
Requires-Dist: numpy
Requires-Dist: scipy
Requires-Dist: scikit-learn
Requires-Dist: clone
Requires-Dist: pandas
